cable/__init__.py
cable/version.py
cable-0.1.dist-info/LICENSE
cable-0.1.dist-info/METADATA
cable-0.1.dist-info/WHEEL
cable-0.1.dist-info/top_level.txt
cable-0.1.dist-info/RECORD
